xaal/__init__.py
xaal/influxdb/__init__.py
xaal/influxdb/__main__.py
xaal/influxdb/influxdblogger.py
xaal_influxdb-0.1.3.dist-info/METADATA
xaal_influxdb-0.1.3.dist-info/WHEEL
xaal_influxdb-0.1.3.dist-info/top_level.txt
xaal_influxdb-0.1.3.dist-info/RECORD
