Metadata-Version: 2.4
Name: xaal.influxdb
Version: 0.1.3
Summary: xAAL device for InfluxDB logging
Author-email: Pierre-Henri Horrein <freki@frekilabs.fr>
License-Expression: GPL-3.0-or-later
Project-URL: Homepage, https://recherche.imt-atlantique.fr/xaal/
Project-URL: Documentation, https://gitlab.imt-atlantique.fr/xaal/code/python/-/blob/main/devices/loggers/influxdb/README.rst
Project-URL: Source, https://gitlab.imt-atlantique.fr/xaal/code/python/-/tree/main/devices/loggers/influxdb
Keywords: xaal,influxdb
Classifier: Programming Language :: Python
Classifier: Topic :: Software Development :: Libraries :: Python Modules
Requires-Dist: xaal.lib
Requires-Dist: influxdb
